smart_ip_info/__init__.py
smart_ip_info/__main__.py
smart_ip_info/cli.py
smart_ip_info/ip_info.py
smart_ip_info/services.py
smart_ip_info-0.1.3.dist-info/licenses/LICENSE
smart_ip_info-0.1.3.dist-info/METADATA
smart_ip_info-0.1.3.dist-info/WHEEL
smart_ip_info-0.1.3.dist-info/entry_points.txt
smart_ip_info-0.1.3.dist-info/top_level.txt
smart_ip_info-0.1.3.dist-info/RECORD
