Metadata-Version: 2.4
Name: smart-ip-info
Version: 0.1.3
Summary: A simple tool to get information about IP addresses.
Author-email: "A.A. Suvorov" <smartlegiondev@email.com>
License-Expression: BSD-3-Clause
Project-URL: Homepage, https://github.com/smartlegionlab/smart-ip-info
Project-URL: Documentation, https://github.com/smartlegionlab/smart-ip-info#readme
Keywords: ip,geo,cli,network
Classifier: Programming Language :: Python :: 3
Classifier: Operating System :: OS Independent
Classifier: Intended Audience :: System Administrators
Classifier: Topic :: Utilities
Requires-Python: >=3.8
License-File: LICENSE
Dynamic: license-file
